[{"sport_key": "soccer_brazil_campeonato", "sport_nice": "Brazil S\u00e9rie A", "teams": ["Atletico Goianiense", "Goi\u00e1s"], "commence_time": 1607382000, "home_team": "Atletico Goianiense", "sites": [{"site_key": "betclic", "site_nice": "Betclic", "last_update": 1607374500, "odds": {"h2h": [1.67, 5.2, 3.73]}}, {"site_key": "marathonbet", "site_nice": "Marathon Bet", "last_update": 1607374451, "odds": {"h2h": [1.69, 5.05, 3.85]}}, {"site_key": "betway", "site_nice": "Betway", "last_update": 1607374453, "odds": {"h2h": [1.67, 5.25, 3.6]}}, {"site_key": "betfair", "site_nice": "Betfair", "last_update": 1607374390, "odds": {"h2h": [1.74, 5.7, 3.95], "h2h_lay": [1.75, 5.9, 4.1]}}, {"site_key": "unibet", "site_nice": "Unibet", "last_update": 1607374449, "odds": {"h2h": [1.61, 4.9, 3.6]}}, {"site_key": "sport888", "site_nice": "888sport", "last_update": 1607374451, "odds": {"h2h": [1.61, 4.9, 3.6]}}, {"site_key": "intertops", "site_nice": "Intertops", "last_update": 1607373841, "odds": {"h2h": [1.62, 5.0, 3.6]}}], "sites_count": 7}, {"sport_key": "soccer_brazil_campeonato", "sport_nice": "Brazil S\u00e9rie A", "teams": ["Botafogo", "Sao Paulo"], "commence_time": 1607560200, "home_team": "Sao Paulo", "sites": [{"site_key": "betway", "site_nice": "Betway", "last_update": 1607374453, "odds": {"h2h": [6.5, 1.5, 4.0]}}, {"site_key": "betclic", "site_nice": "Betclic", "last_update": 1607374500, "odds": {"h2h": [6.55, 1.49, 4.25]}}, {"site_key": "mybookieag", "site_nice": "MyBookie.ag", "last_update": 1607374452, "odds": {"h2h": [6.47, 1.48, 4.2]}}, {"site_key": "betfair", "site_nice": "Betfair", "last_update": 1607374390, "odds": {"h2h": [7.4, 1.48, 4.7], "h2h_lay": [8.6, 1.5, 5.1]}}, {"site_key": "bookmaker", "site_nice": "Bookmaker", "last_update": 1607374334, "odds": {"h2h": [6.37, 1.47, 4.14]}}, {"site_key": "unibet", "site_nice": "Unibet", "last_update": 1607374449, "odds": {"h2h": [6.0, 1.45, 4.0]}}, {"site_key": "sport888", "site_nice": "888sport", "last_update": 1607374451, "odds": {"h2h": [6.0, 1.45, 4.0]}}, {"site_key": "intertops", "site_nice": "Intertops", "last_update": 1607373841, "odds": {"h2h": [6.5, 1.44, 4.0]}}], "sites_count": 8}, {"sport_key": "soccer_brazil_campeonato", "sport_nice": "Brazil S\u00e9rie A", "teams": ["Corinthians", "Sao Paulo"], "commence_time": 1607894160, "home_team": "Corinthians", "sites": [], "sites_count": 0}]